skill_wikipedia/LICENSE
skill_wikipedia/LICENSE.md
skill_wikipedia/README.md
skill_wikipedia/__init__.py
skill_wikipedia/pic.py
skill_wikipedia/skill.json
skill_wikipedia/version.py
skill_wikipedia/locale/ca-es/More.voc
skill_wikipedia/locale/ca-es/no entry found.dialog
skill_wikipedia/locale/ca-es/searching.dialog
skill_wikipedia/locale/ca-es/thats all.dialog
skill_wikipedia/locale/ca-es/wiki.intent
skill_wikipedia/locale/ca-es/wikiroulette.dialog
skill_wikipedia/locale/ca-es/wikiroulette.intent
skill_wikipedia/locale/en-us/More.voc
skill_wikipedia/locale/en-us/no entry found.dialog
skill_wikipedia/locale/en-us/searching.dialog
skill_wikipedia/locale/en-us/thats all.dialog
skill_wikipedia/locale/en-us/wiki.intent
skill_wikipedia/locale/en-us/wikiroulette.dialog
skill_wikipedia/locale/en-us/wikiroulette.intent
skill_wikipedia/neon_skill_wikipedia.egg-info/PKG-INFO
skill_wikipedia/neon_skill_wikipedia.egg-info/SOURCES.txt
skill_wikipedia/neon_skill_wikipedia.egg-info/dependency_links.txt
skill_wikipedia/neon_skill_wikipedia.egg-info/entry_points.txt
skill_wikipedia/neon_skill_wikipedia.egg-info/requires.txt
skill_wikipedia/neon_skill_wikipedia.egg-info/top_level.txt
skill_wikipedia/ui/jumping.gif
neon_skill_wikipedia-1.0.2.dist-info/LICENSE
neon_skill_wikipedia-1.0.2.dist-info/LICENSE.md
neon_skill_wikipedia-1.0.2.dist-info/METADATA
neon_skill_wikipedia-1.0.2.dist-info/WHEEL
neon_skill_wikipedia-1.0.2.dist-info/entry_points.txt
neon_skill_wikipedia-1.0.2.dist-info/top_level.txt
neon_skill_wikipedia-1.0.2.dist-info/RECORD
