Metadata-Version: 2.1
Name: neon-skill-wikipedia
Version: 1.0.2
Home-page: https://github.com/NeonGeckoCom/skill-wikipedia
Author: Neongecko
Author-email: developers@neon.ai
License: BSD-3-Clause
License-File: LICENSE
License-File: LICENSE.md
Requires-Dist: wikipedia-for-humans ~=0.2.3
Requires-Dist: ovos-utils >=0.0.28,~=0.0
Requires-Dist: neon-utils ~=1.0
Requires-Dist: ovos-workshop ~=0.0.15
Requires-Dist: wikipedia-api ~=0.5.8
